canterburycommuto/CanterburyCommuto.py
canterburycommuto/Computations.py
canterburycommuto/HelperFunctions.py
canterburycommuto/PlotMaps.py
canterburycommuto/Sample.py
canterburycommuto/__init__.py
canterburycommuto/__main__.py
canterburycommuto/config.yaml
canterburycommuto/notebooks/api_response_cache.pkl
canterburycommuto/notebooks/origin_destination_test.csv
canterburycommuto/notebooks/origin_destination_test_ID.csv
canterburycommuto/notebooks/test_by_import.ipynb
canterburycommuto/notebooks/validation_errors_timing.log
canterburycommuto/notebooks/results/Apple1.csv
canterburycommuto/notebooks/results/Apple1.log
canterburycommuto/notebooks/results/Apple2.csv
canterburycommuto/notebooks/results/Apple2.log
canterburycommuto/notebooks/results/Tom.csv
canterburycommuto/notebooks/results/Tom.log
canterburycommuto/notebooks/results/api_response_cache.pkl
canterburycommuto/notebooks/results/banana.csv
canterburycommuto/notebooks/results/banana.log
canterburycommuto/notebooks/results/closest_nodes_buffer_only_overlap-2025-06-11_11-34-07_27767.csv
canterburycommuto/notebooks/results/closest_nodes_buffer_only_overlap-2025-06-11_11-34-07_27767.log
canterburycommuto/notebooks/results/exact_intersection_buffer_only_overlap-2025-06-11_11-34-12_36918.csv
canterburycommuto/notebooks/results/exact_intersection_buffer_only_overlap-2025-06-11_11-34-12_36918.log
canterburycommuto/notebooks/results/exact_intersection_buffer_only_overlap-2025-06-11_20-54-51_70618.csv
canterburycommuto/notebooks/results/exact_intersection_buffer_only_overlap-2025-06-11_20-54-51_70618.log
canterburycommuto/notebooks/results/grape.csv
canterburycommuto/notebooks/results/grape.log
canterburycommuto/notebooks/results/iron man.csv
canterburycommuto/notebooks/results/iron man.log
canterburycommuto/notebooks/results/mission impossible.csv
canterburycommuto/notebooks/results/mission impossible.log
canterburycommuto/notebooks/results/outputRec-2025-06-11_11-33-57_71504.csv
canterburycommuto-0.2.5.dist-info/licenses/LICENSE
canterburycommuto-0.2.5.dist-info/WHEEL
canterburycommuto-0.2.5.dist-info/METADATA
canterburycommuto-0.2.5.dist-info/RECORD
