Metadata-Version: 2.4
Name: canterburycommuto
Version: 0.2.5
Summary: CanterburyCommuto
Author-email: Peirong Shi <shipr1003@gmail.com>
Classifier: License :: OSI Approved :: MIT License
License-File: LICENSE
Requires-Dist: requests
Requires-Dist: polyline
Requires-Dist: matplotlib
Requires-Dist: shapely
Requires-Dist: pyproj
Requires-Dist: folium
Requires-Dist: ipython
Requires-Dist: pyyaml
Requires-Dist: pydantic
Project-URL: Home, https://github.com/PeirongShi/CanterburyCommuto
